jit/__init__.py
jit/app.py
jit/constants.py
jit/exceptions.py
jit/main.py
jit/models.py
jit/services/__init__.py
jit/services/cache_service.py
jit/services/config_service.py
jit/services/git_service.py
jit/services/jira_service.py
jit/ui/__init__.py
jit/ui/prompts.py
jit/ui/selectors.py
jit/utils/__init__.py
jit/utils/logger.py
le_jit-0.1.3.dist-info/METADATA
le_jit-0.1.3.dist-info/WHEEL
le_jit-0.1.3.dist-info/entry_points.txt
le_jit-0.1.3.dist-info/RECORD
