Metadata-Version: 2.3
Name: le-jit
Version: 0.1.3
Summary: 
Author: Tomer Lev
Author-email: levtomer66@gmail.com
Requires-Python: >=3.13,<4.0
Classifier: Programming Language :: Python :: 3
Classifier: Programming Language :: Python :: 3.13
Requires-Dist: InquirerPy (>=0.3.4,<0.4.0)
Requires-Dist: jira (>=3.10.5,<4.0.0)
Requires-Dist: pyyaml (>=6.0.2,<7.0.0)
Requires-Dist: typer[all] (>=0.16.1,<0.17.0)
